ligoogle/__init__.py
ligoogle/__main__.py
ligoogle/app_google.py
ligoogle-3.0.4.dist-info/METADATA
ligoogle-3.0.4.dist-info/WHEEL
ligoogle-3.0.4.dist-info/licenses/LICENSE
ligoogle-3.0.4.dist-info/RECORD
