Metadata-Version: 2.1
Name: ligoogle
Version: 3.0.4
Summary: A (unofficial) google service for linux terminals
Project-URL: Homepage, https://github.com/carrotscript/ligoogle
Project-URL: Bug Tracker, https://github.com/carrotscript/ligoogle/issues
Author-email: Arjun Jakkipally <jakkipally@gmail.com>
License-File: LICENSE
Classifier: Operating System :: Unix
Classifier: Programming Language :: Python :: 3
Requires-Python: >=3.6
Requires-Dist: magic-google
